{
    "version": "0.0.0",
    "channel_order": "AGTC",
    "mappings": [
        {
            "codeword": [
                {
                    "r": 0,
                    "c": 0,
                    "v": 1.0
                },
                {
                    "r": 1,
                    "c": 1,
                    "v": 1.0
                },
                {
                    "r": 2,
                    "c": 3,
                    "v": 1.0
                }
            ],
            "target": "PB2"
        },
        {
            "codeword": [
                {
                    "r": 0,
                    "c": 3,
                    "v": 1.0
                },
                {
                    "r": 1,
                    "c": 1,
                    "v": 1.0
                },
                {
                    "r": 2,
                    "c": 3,
                    "v": 1.0
                }
            ],
            "target": "PB1"
        },
        {
            "codeword": [
                {
                    "r": 0,
                    "c": 1,
                    "v": 1.0
                },
                {
                    "r": 1,
                    "c": 1,
                    "v": 1.0
                },
                {
                    "r": 2,
                    "c": 3,
                    "v": 1.0
                }
            ],
            "target": "PA"
        },
        {
            "codeword": [
                {
                    "r": 0,
                    "c": 2,
                    "v": 1.0
                },
                {
                    "r": 1,
                    "c": 0,
                    "v": 1.0
                },
                {
                    "r": 2,
                    "c": 3,
                    "v": 1.0
                }
            ],
            "target": "HA"
        },
        {
            "codeword": [
                {
                    "r": 0,
                    "c": 2,
                    "v": 1.0
                },
                {
                    "r": 1,
                    "c": 3,
                    "v": 1.0
                },
                {
                    "r": 2,
                    "c": 3,
                    "v": 1.0
                }
            ],
            "target": "NP"
        },
        {
            "codeword": [
                {
                    "r": 0,
                    "c": 2,
                    "v": 1.0
                },
                {
                    "r": 1,
                    "c": 2,
                    "v": 1.0
                },
                {
                    "r": 2,
                    "c": 3,
                    "v": 1.0
                }
            ],
            "target": "NA"
        },
        {
            "codeword": [
                {
                    "r": 0,
                    "c": 2,
                    "v": 1.0
                },
                {
                    "r": 1,
                    "c": 1,
                    "v": 1.0
                },
                {
                    "r": 2,
                    "c": 0,
                    "v": 1.0
                }
            ],
            "target": "M"
        },
        {
            "codeword": [
                {
                    "r": 0,
                    "c": 2,
                    "v": 1.0
                },
                {
                    "r": 1,
                    "c": 1,
                    "v": 1.0
                },
                {
                    "r": 2,
                    "c": 2,
                    "v": 1.0
                }
            ],
            "target": "NS"
        }
    ]
}